{
  "key": "GT-114", 
  "fields": {
    "comment": {
      "total": 1, 
      "startAt": 0, 
      "comments": [
        {
          "body": "Given IGE's mission of making Globus more European-friendly, they are likely to care a lot about Internationalization (i18n).  So we should figure out what work is involved in bringing this up-to-date with i18n, and then work with IGE to figure out who should do what.\n", 
          "updateAuthor": {
            "displayName": "Steve Tuecke", 
            "name": "tuecke", 
            "self": "https://globus.atlassian.net/rest/api/2/user?username=tuecke", 
            "avatarUrls": {
              "24x24": "https://globus.atlassian.net/secure/useravatar?size=small&avatarId=10162", 
              "32x32": "https://globus.atlassian.net/secure/useravatar?size=medium&avatarId=10162", 
              "48x48": "https://globus.atlassian.net/secure/useravatar?avatarId=10162", 
              "16x16": "https://globus.atlassian.net/secure/useravatar?size=xsmall&avatarId=10162"
            }, 
            "emailAddress": "tuecke@uchicago.edu", 
            "key": "tuecke", 
            "active": true, 
            "timeZone": "America/Chicago"
          }, 
          "created": "2010-03-31T21:05:21.505-0500", 
          "self": "https://globus.atlassian.net/rest/api/2/issue/11433/comment/11245", 
          "author": {
            "displayName": "Steve Tuecke", 
            "name": "tuecke", 
            "self": "https://globus.atlassian.net/rest/api/2/user?username=tuecke", 
            "avatarUrls": {
              "24x24": "https://globus.atlassian.net/secure/useravatar?size=small&avatarId=10162", 
              "32x32": "https://globus.atlassian.net/secure/useravatar?size=medium&avatarId=10162", 
              "48x48": "https://globus.atlassian.net/secure/useravatar?avatarId=10162", 
              "16x16": "https://globus.atlassian.net/secure/useravatar?size=xsmall&avatarId=10162"
            }, 
            "emailAddress": "tuecke@uchicago.edu", 
            "key": "tuecke", 
            "active": true, 
            "timeZone": "America/Chicago"
          }, 
          "updated": "2010-03-31T21:05:21.505-0500", 
          "id": "11245"
        }
      ], 
      "maxResults": 1
    }, 
    "customfield_10480": null, 
    "customfield_10282": null, 
    "creator": {
      "displayName": "Joe Bester", 
      "name": "bester", 
      "self": "https://globus.atlassian.net/rest/api/2/user?username=bester", 
      "avatarUrls": {
        "24x24": "https://globus.atlassian.net/secure/useravatar?size=small&avatarId=10162", 
        "32x32": "https://globus.atlassian.net/secure/useravatar?size=medium&avatarId=10162", 
        "48x48": "https://globus.atlassian.net/secure/useravatar?avatarId=10162", 
        "16x16": "https://globus.atlassian.net/secure/useravatar?size=xsmall&avatarId=10162"
      }, 
      "emailAddress": "bester@mcs.anl.gov", 
      "key": "bester", 
      "active": true, 
      "timeZone": "America/New_York"
    }, 
    "customfield_10600": null, 
    "customfield_10601": null, 
    "customfield_10602": null, 
    "labels": [], 
    "customfield_10604": null, 
    "customfield_10380": "0|100br4:", 
    "watches": {
      "self": "https://globus.atlassian.net/rest/api/2/issue/GT-114/watchers", 
      "watchCount": 0, 
      "isWatching": false
    }, 
    "assignee": null, 
    "lastViewed": null, 
    "customfield_10287": null, 
    "customfield_10280": "1905", 
    "issuelinks": [], 
    "customfield_10283": null, 
    "customfield_10780": "com.atlassian.servicedesk.plugins.approvals.internal.customfield.ApprovalsCFValue@d56edb", 
    "summary": "i18n rules in installer don't work", 
    "customfield_10288": "2010-03-31T21:05:21.505-0500", 
    "aggregateprogress": {
      "progress": 0, 
      "total": 0
    }, 
    "customfield_10024": null, 
    "project": {
      "name": "Globus Toolkit", 
      "self": "https://globus.atlassian.net/rest/api/2/project/10363", 
      "avatarUrls": {
        "24x24": "https://globus.atlassian.net/secure/projectavatar?size=small&pid=10363&avatarId=10011", 
        "32x32": "https://globus.atlassian.net/secure/projectavatar?size=medium&pid=10363&avatarId=10011", 
        "48x48": "https://globus.atlassian.net/secure/projectavatar?pid=10363&avatarId=10011", 
        "16x16": "https://globus.atlassian.net/secure/projectavatar?size=xsmall&pid=10363&avatarId=10011"
      }, 
      "projectCategory": {
        "self": "https://globus.atlassian.net/rest/api/2/projectCategory/10040", 
        "id": "10040", 
        "name": "Globus Toolkit", 
        "description": "Globus Toolkit - all components"
      }, 
      "key": "GT", 
      "id": "10363"
    }, 
    "votes": {
      "hasVoted": false, 
      "self": "https://globus.atlassian.net/rest/api/2/issue/GT-114/votes", 
      "votes": 0
    }, 
    "customfield_10598": null, 
    "customfield_10599": null, 
    "customfield_10597": null, 
    "fixVersions": [], 
    "priority": {
      "iconUrl": "https://globus.atlassian.net/images/icons/priorities/major.svg", 
      "self": "https://globus.atlassian.net/rest/api/2/priority/3", 
      "name": "Major", 
      "id": "3"
    }, 
    "timespent": null, 
    "attachment": [], 
    "aggregatetimeestimate": null, 
    "progress": {
      "progress": 0, 
      "total": 0
    }, 
    "status": {
      "statusCategory": {
        "name": "To Do", 
        "self": "https://globus.atlassian.net/rest/api/2/statuscategory/2", 
        "id": 2, 
        "key": "new", 
        "colorName": "blue-gray"
      }, 
      "description": "The issue is open and ready for the assignee to start work on it.", 
      "self": "https://globus.atlassian.net/rest/api/2/status/1", 
      "iconUrl": "https://globus.atlassian.net/images/icons/statuses/open.png", 
      "id": "1", 
      "name": "Open"
    }, 
    "updated": "2012-05-02T14:36:48.690-0500", 
    "customfield_10603": null, 
    "subtasks": [], 
    "description": "The i18n rules in the installer's makefile for 5.0.0 and 5.0.1 don't work, as the i18n code and bundle aren't included in the installer. Either the rules should be eliminated or the i18n code should be included in the installer.", 
    "reporter": {
      "displayName": "Joe Bester", 
      "name": "bester", 
      "self": "https://globus.atlassian.net/rest/api/2/user?username=bester", 
      "avatarUrls": {
        "24x24": "https://globus.atlassian.net/secure/useravatar?size=small&avatarId=10162", 
        "32x32": "https://globus.atlassian.net/secure/useravatar?size=medium&avatarId=10162", 
        "48x48": "https://globus.atlassian.net/secure/useravatar?avatarId=10162", 
        "16x16": "https://globus.atlassian.net/secure/useravatar?size=xsmall&avatarId=10162"
      }, 
      "emailAddress": "bester@mcs.anl.gov", 
      "key": "bester", 
      "active": true, 
      "timeZone": "America/New_York"
    }, 
    "worklog": {
      "worklogs": [], 
      "total": 0, 
      "startAt": 0, 
      "maxResults": 20
    }, 
    "customfield_10020": null, 
    "timeoriginalestimate": null, 
    "environment": null, 
    "customfield_10680": null, 
    "customfield_10681": null, 
    "aggregatetimeoriginalestimate": null, 
    "created": "2010-03-31T08:20:37.925-0500", 
    "versions": [], 
    "resolutiondate": null, 
    "workratio": -1, 
    "aggregatetimespent": null, 
    "timetracking": {}, 
    "components": [
      {
        "self": "https://globus.atlassian.net/rest/api/2/component/10327", 
        "id": "10327", 
        "name": "Common Libs"
      }
    ], 
    "issuetype": {
      "name": "Bug", 
      "self": "https://globus.atlassian.net/rest/api/2/issuetype/1", 
      "iconUrl": "https://globus.atlassian.net/secure/viewavatar?size=xsmall&avatarId=11043&avatarType=issuetype", 
      "subtask": false, 
      "avatarId": 11043, 
      "id": "1", 
      "description": "A problem which impairs or prevents the functions of the product."
    }, 
    "resolution": null, 
    "timeestimate": null
  }, 
  "self": "https://globus.atlassian.net/rest/api/2/issue/11433", 
  "id": "11433", 
  "expand": "renderedFields,names,schema,operations,editmeta,changelog,versionedRepresentations"
}